mkdocs_windows_98/404.html
mkdocs_windows_98/__init__.py
mkdocs_windows_98/head.html
mkdocs_windows_98/main.html
mkdocs_windows_98/mkdocs_theme.yml
mkdocs_windows_98/scripts.html
mkdocs_windows_98/taskbar.html
mkdocs_windows_98/window-page-content.html
mkdocs_windows_98/css/mkdocs-windows-98.css
mkdocs_windows_98/icons/browse-ui-icons-grayscale.png
mkdocs_windows_98/icons/browse-ui-icons.png
mkdocs_windows_98/icons/windows-98-icon.png
mkdocs_windows_98-0.5.0.dist-info/LICENSE
mkdocs_windows_98-0.5.0.dist-info/METADATA
mkdocs_windows_98-0.5.0.dist-info/WHEEL
mkdocs_windows_98-0.5.0.dist-info/entry_points.txt
mkdocs_windows_98-0.5.0.dist-info/top_level.txt
mkdocs_windows_98-0.5.0.dist-info/RECORD
