Metadata-Version: 2.1
Name: mkdocs-windows-98
Version: 0.5.0
Summary: Windows 98 MkDocs Theme
Author-email: Useless DevLab <useless.devlab@gmail.com>
Project-URL: Documentation, https://Useless-DevLab.github.io/mkdocs-windows-98/
Project-URL: Issues, https://github.com/Useless-DevLab/mkdocs-windows-98/issues
Project-URL: Source, https://github.com/Useless-DevLab/mkdocs-windows-98
Classifier: Development Status :: 3 - Alpha
Classifier: Environment :: Console
Classifier: Operating System :: POSIX
Classifier: Intended Audience :: Developers
Classifier: Intended Audience :: Information Technology
Classifier: Intended Audience :: System Administrators
Classifier: Topic :: Software Development :: Build Tools
Classifier: Natural Language :: English
Classifier: Programming Language :: Python :: 3.9
Classifier: Topic :: Utilities
Classifier: Topic :: Software Development :: Documentation
Requires-Python: >=3.9
License-File: LICENSE
Requires-Dist: mkdocs >=1.5.3
Provides-Extra: lint
Requires-Dist: djlint ==1.34.0 ; extra == 'lint'
Requires-Dist: yamllint ==1.32.0 ; extra == 'lint'
